LICENSE
MANIFEST.in
README.rst
setup.cfg
setup.py
test/test_adhoc_deployer.py
test/test_deployer.py
test/test_test_runner.py
test/test_test_runner_helper.py
test/test_test_utils.py
test/test_utils.py
test/test_zopkio.py
zopkio/__init__.py
zopkio/__main__.py
zopkio/adhoc_deployer.py
zopkio/configobj.py
zopkio/constants.py
zopkio/deployer.py
zopkio/error_messages.py
zopkio/recipes.py
zopkio/remote_host_helper.py
zopkio/reporter.py
zopkio/results_collector.py
zopkio/runtime.py
zopkio/test_runner.py
zopkio/test_runner_helper.py
zopkio/test_utils.py
zopkio/testobj.py
zopkio/utils.py
zopkio/ztests.py
zopkio.egg-info/PKG-INFO
zopkio.egg-info/SOURCES.txt
zopkio.egg-info/dependency_links.txt
zopkio.egg-info/entry_points.txt
zopkio.egg-info/requires.txt
zopkio.egg-info/top_level.txt
zopkio/web_resources/config_page.html
zopkio/web_resources/diff.html
zopkio/web_resources/footer.html
zopkio/web_resources/header.html
zopkio/web_resources/landing_page.html
zopkio/web_resources/logs_page.html
zopkio/web_resources/script.js
zopkio/web_resources/style.css
zopkio/web_resources/test_page.html
zopkio/web_resources/topbar.html