Metadata-Version: 1.1
Name: zopkio
Version: 0.2.4
Summary: Zopkio: A distributed testing framework
Home-page: http://github.com/linkedin/zopkio
Author: Joshua Ehrlich
Author-email: jehrlich@linkedin.com,zopkio@googlegroups.com
License: Apache
Download-URL: https://github.com/linkedin/zopkio/tarball/0.2.4
Platform: UNKNOWN
Classifier: Intended Audience :: Developers
Classifier: License :: OSI Approved :: Apache Software License
Classifier: Programming Language :: Python
Classifier: Programming Language :: Python :: 2.6
Classifier: Programming Language :: Python :: 2.7
Classifier: Programming Language :: Python :: 3
Classifier: Programming Language :: Python :: 3.3
